project_diagnose/__init__.py
project_diagnose/analyzer.py
project_diagnose/cli.py
project_diagnose/config_schema.py
project_diagnose/rendering.py
project_diagnose/web.py
project_diagnose/static/script.js
project_diagnose/static/style.css
project_diagnose/templates/index.html
project_diagnose/templates/settings.html
project_diagnose-0.1.16.dist-info/licenses/LICENSE
project_diagnose-0.1.16.dist-info/METADATA
project_diagnose-0.1.16.dist-info/WHEEL
project_diagnose-0.1.16.dist-info/entry_points.txt
project_diagnose-0.1.16.dist-info/top_level.txt
project_diagnose-0.1.16.dist-info/RECORD
