Metadata-Version: 2.4
Name: project-diagnose
Version: 0.1.16
Summary: AI-анализатор хаоса проекта и web-интерфейс для просмотра отчётов.
Home-page: https://github.com/yourname/project-diagnose
Author: Razmakh
Classifier: Programming Language :: Python :: 3
Classifier: License :: OSI Approved :: MIT License
Classifier: Operating System :: OS Independent
Classifier: Environment :: Console
Classifier: Topic :: Software Development :: Quality Assurance
Requires-Python: >=3.8
License-File: LICENSE
Requires-Dist: flask
Requires-Dist: pydantic>=2.0
Dynamic: author
Dynamic: classifier
Dynamic: description
Dynamic: description-content-type
Dynamic: home-page
Dynamic: license-file
Dynamic: requires-dist
Dynamic: requires-python
Dynamic: summary
